[{"A_Profit":650,"A_Cost":2400,"A_Revenue":2700,"B_Profit":580,"B_Cost":2100,"B_Revenue":1800,"C_Profit":800,"C_Cost":2200,"C_Revenue":900,"D_Profit":480,"D_Cost":2350,"D_Revenue":500},
	{"A_Profit":810,"A_Cost":1870,"A_Revenue":2450,"B_Profit":1250,"B_Cost":2200,"B_Revenue":2000,"C_Profit":850,"C_Cost":2900,"C_Revenue":700,"D_Profit":300,"D_Cost":1200,"D_Revenue":600},
	{"A_Profit":1300,"A_Cost":1500,"A_Revenue":2550,"B_Profit":1350,"B_Cost":950,"B_Revenue":1500,"C_Profit":640,"C_Cost":900,"C_Revenue":900,"D_Profit":670,"D_Cost":700,"D_Revenue":520},
	{"A_Profit":1700,"A_Cost":2200,"A_Revenue":2600,"B_Profit":1500,"B_Cost":1200,"B_Revenue":1200,"C_Profit":1500,"C_Cost":2600,"C_Revenue":800,"D_Profit":1150,"D_Cost":2350,"D_Revenue":600},
	{"A_Profit":2000,"A_Cost":1600,"A_Revenue":2600,"B_Profit":2000,"B_Cost":1900,"B_Revenue":1600,"C_Profit":1600,"C_Cost":2050,"C_Revenue":900,"D_Profit":1380,"D_Cost":1050,"D_Revenue":510},
	{"C_Profit":1800,"C_Cost":2800,"C_Revenue":1000,"D_Profit":1950,"D_Cost":1800,"D_Revenue":550},
	{"C_Profit":2200,"C_Cost":2000,"C_Revenue":800,"D_Profit":2050,"D_Cost":2600,"D_Revenue":550}]